Metadata-Version: 2.1
Name: pyneql
Version: 0.1.0
Summary: A SPARQL wrapper to query named entities in the semantic web
Home-page: https://github.com/Valerie-Hanoka/PyNeQL
Author: Valérie Hanoka
Author-email: valerieh@protonmail.com
License: BSD 2-Clause License
Requires-Dist: nose (>=1.3.7)
Requires-Dist: python-coveralls (>=2.9.1)
Requires-Dist: six (>=1.11.0)
Requires-Dist: aenum (>=2.1.2)
Requires-Dist: requests (>=2.18.4)
Requires-Dist: fuzzywuzzy (>=0.16.0)
Requires-Dist: python-dateutil (>=2.7.2)
Requires-Dist: future
